ebuildtester/__init__.py
ebuildtester/atom.py
ebuildtester/config.py
ebuildtester/docker.py
ebuildtester/main.py
ebuildtester/options.py
ebuildtester/parse.py
ebuildtester/utils.py
ebuildtester-47.dist-info/licenses/COPYING
ebuildtester-47.dist-info/METADATA
ebuildtester-47.dist-info/WHEEL
ebuildtester-47.dist-info/entry_points.txt
ebuildtester-47.dist-info/top_level.txt
ebuildtester-47.dist-info/RECORD
