Metadata-Version: 2.4
Name: ebuildtester
Version: 47
Summary: A container approach to test a Gentoo package within a clean stage3 container
Home-page: http://ebuildtester.readthedocs.io/
Author: Nicolas Bock
Author-email: nicolasbock@gmail.com
License: BSD
License-File: COPYING
Dynamic: author
Dynamic: author-email
Dynamic: description
Dynamic: description-content-type
Dynamic: home-page
Dynamic: license
Dynamic: license-file
Dynamic: summary
